bepy/setup.py
bepy-1.0.0.dist-info/LICENSE
bepy-1.0.0.dist-info/METADATA
bepy-1.0.0.dist-info/WHEEL
bepy-1.0.0.dist-info/top_level.txt
bepy-1.0.0.dist-info/RECORD
