Metadata-Version: 2.1
Name: bepy
Version: 1.0.0
Summary: A framework for materials characterization data collected that facilitates post analysis
Home-page: https://github.com/lgriffin39/bepy
Author: Lee Griffin
Author-email: lgriffin39@gatech.edu
License: MIT
Platform: UNKNOWN
Requires-Dist: numpy
Requires-Dist: pandas
Requires-Dist: matplotlib
Requires-Dist: scipy
